catalyze/__init__.py
catalyze/__main__.py
catalyze/client.py
catalyze/config.py
catalyze/git.py
catalyze/output.py
catalyze/project.py
catalyze/commands/__init__.py
catalyze/commands/associate.py
catalyze/commands/backup.py
catalyze/commands/console.py
catalyze/commands/dashboard.py
catalyze/commands/db.py
catalyze/commands/environments.py
catalyze/commands/metrics.py
catalyze/commands/rake.py
catalyze/commands/redeploy.py
catalyze/commands/status.py
catalyze/commands/support_ids.py
catalyze/commands/users.py
catalyze/commands/variables.py
catalyze/commands/worker.py
catalyze/helpers/__init__.py
catalyze/helpers/AESCrypto.py
catalyze/helpers/environment_variables.py
catalyze/helpers/environments.py
catalyze/helpers/jobs.py
catalyze/helpers/logs.py
catalyze/helpers/pods.py
catalyze/helpers/services.py
catalyze/helpers/tasks.py
catalyze-1.4.2.dist-info/DESCRIPTION.rst
catalyze-1.4.2.dist-info/entry_points.txt
catalyze-1.4.2.dist-info/METADATA
catalyze-1.4.2.dist-info/metadata.json
catalyze-1.4.2.dist-info/RECORD
catalyze-1.4.2.dist-info/top_level.txt
catalyze-1.4.2.dist-info/WHEEL
