Metadata-Version: 2.0
Name: catalyze
Version: 1.4.2
Summary: CLI for Catalyze Platform-as-a-Service interaction
Home-page: https://github.com/catalyzeio/catalyze-paas-cli
Author: Catalyze
Author-email: support@catalyze.io
License: UNKNOWN
Platform: UNKNOWN
Requires-Dist: cffi (==0.9.2)
Requires-Dist: click (==3.3)
Requires-Dist: cryptography (==0.8.2)
Requires-Dist: enum34 (==1.0.4)
Requires-Dist: ndg-httpsclient (==0.3.3)
Requires-Dist: pyOpenSSL (>=0.15.1)
Requires-Dist: pyasn1 (==0.1.7)
Requires-Dist: pycparser (==2.10)
Requires-Dist: pycrypto (==2.6.1)
Requires-Dist: requests (>=2.7.0)
Requires-Dist: six (==1.9.0)
Requires-Dist: ws4py (==0.3.4)
